crm_module_vtp/__init__.py
crm_module_vtp/client.py
crm_module_vtp-0.1.1.dist-info/METADATA
crm_module_vtp-0.1.1.dist-info/WHEEL
crm_module_vtp-0.1.1.dist-info/entry_points.txt
crm_module_vtp-0.1.1.dist-info/top_level.txt
crm_module_vtp-0.1.1.dist-info/RECORD
