Metadata-Version: 2.1
Name: crm_module_vtp
Version: 0.1.1
Summary: A CRM integration module with VTP
Classifier: Programming Language :: Python :: 3
Classifier: License :: OSI Approved :: MIT License
Classifier: Operating System :: OS Independent
